{
  "poolConfig": {
    "poolConfigurator": "0x8145eddDf43f50276641b55bd3AD95944510021E",
    "poolConfiguratorImpl": "0x79b5e91037AE441dE0d9e6fd3Fd85b96B83d4E93",
    "priceOracleSentinel": "0x0000000000000000000000000000000000000000",
    "oracle": "0xEBd36016B3eD09D4693Ed4251c67Bd858c3c7C9C",
    "poolImpl": "0xCf85FF1c37c594a10195F7A9Ab85CBb0a03f69dE",
    "pool": "0x794a61358D6845594F94dc1DB02A252b5b4814aD",
    "poolAddressesProvider": "0xa97684ead0e402dC232d5A977953DF7ECBaB3CDb",
    "protocolDataProvider": "0x50ddd0Cd4266299527d25De9CBb55fE0EB8dAc30"
  },
  "chainId": 43114,
  "eModes": {
    "1": {
      "ltv": 9700,
      "priceSource": "0x0000000000000000000000000000000000000000",
      "liquidationBonus": 10100,
      "eModeCategory": 1,
      "label": "Stablecoins",
      "liquidationThreshold": 9750
    },
    "2": {
      "liquidationThreshold": 9500,
      "eModeCategory": 2,
      "liquidationBonus": 10100,
      "priceSource": "0x0000000000000000000000000000000000000000",
      "ltv": 9250,
      "label": "AVAX correlated"
    }
  },
  "strategies": {
    "0x79a906e8c998d2fb5C5D66d23c4c5416Fe0168D6": {
      "optimalUsageRatio": 450000000000000000000000000,
      "maxExcessStableToTotalDebtRatio": 800000000000000000000000000,
      "stableRateSlope1": 0,
      "maxExcessUsageRatio": 550000000000000000000000000,
      "optimalStableToTotalDebtRatio": 200000000000000000000000000,
      "variableRateSlope2": 3000000000000000000000000000,
      "baseVariableBorrowRate": 0,
      "stableRateSlope2": 0,
      "variableRateSlope1": 70000000000000000000000000,
      "baseStableBorrowRate": 90000000000000000000000000
    },
    "0xfab05a6aF585da2F96e21452F91E812452996BD3": {
      "baseVariableBorrowRate": 0,
      "variableRateSlope2": 750000000000000000000000000,
      "stableRateSlope2": 750000000000000000000000000,
      "optimalUsageRatio": 800000000000000000000000000,
      "variableRateSlope1": 40000000000000000000000000,
      "maxExcessUsageRatio": 200000000000000000000000000,
      "baseStableBorrowRate": 50000000000000000000000000,
      "maxExcessStableToTotalDebtRatio": 800000000000000000000000000,
      "stableRateSlope1": 5000000000000000000000000,
      "optimalStableToTotalDebtRatio": 200000000000000000000000000
    },
    "0x271f5f8325051f22caDa18FfedD4a805584a232A": {
      "maxExcessUsageRatio": 200000000000000000000000000,
      "optimalStableToTotalDebtRatio": 200000000000000000000000000,
      "stableRateSlope2": 800000000000000000000000000,
      "variableRateSlope1": 38000000000000000000000000,
      "stableRateSlope1": 40000000000000000000000000,
      "variableRateSlope2": 800000000000000000000000000,
      "baseVariableBorrowRate": 10000000000000000000000000,
      "baseStableBorrowRate": 68000000000000000000000000,
      "optimalUsageRatio": 800000000000000000000000000,
      "maxExcessStableToTotalDebtRatio": 800000000000000000000000000
    },
    "0xc76EF342898f1AE7E6C4632627Df683FAD8563DD": {
      "variableRateSlope1": 47200000000000000000000000,
      "baseStableBorrowRate": 87200000000000000000000000,
      "optimalUsageRatio": 650000000000000000000000000,
      "variableRateSlope2": 1442800000000000000000000000,
      "baseVariableBorrowRate": 10000000000000000000000000,
      "stableRateSlope2": 1442800000000000000000000000,
      "optimalStableToTotalDebtRatio": 200000000000000000000000000,
      "maxExcessStableToTotalDebtRatio": 800000000000000000000000000,
      "stableRateSlope1": 47200000000000000000000000,
      "maxExcessUsageRatio": 350000000000000000000000000
    },
    "0xf4a0039F2d4a2EaD5216AbB6Ae4C4C3AA2dB9b82": {
      "optimalUsageRatio": 900000000000000000000000000,
      "variableRateSlope2": 600000000000000000000000000,
      "maxExcessStableToTotalDebtRatio": 800000000000000000000000000,
      "maxExcessUsageRatio": 100000000000000000000000000,
      "baseStableBorrowRate": 50000000000000000000000000,
      "optimalStableToTotalDebtRatio": 200000000000000000000000000,
      "stableRateSlope1": 5000000000000000000000000,
      "stableRateSlope2": 600000000000000000000000000,
      "baseVariableBorrowRate": 0,
      "variableRateSlope1": 40000000000000000000000000
    }
  },
  "reserves": {
    "0xB97EF9Ef8734C71904D8002F8b6Bc66Dd9c48a6E": {
      "debtCeiling": 0,
      "usageAsCollateralEnabled": true,
      "aTokenImpl": "0x1E81af09001aD208BDa68FF022544dB2102A752d",
      "borrowCap": 90000000,
      "liquidationProtocolFee": 1000,
      "eModeCategory": 1,
      "stableBorrowRateEnabled": true,
      "oracleLatestAnswer": 99980000,
      "underlying": "0xB97EF9Ef8734C71904D8002F8b6Bc66Dd9c48a6E",
      "supplyCap": 170000000,
      "interestRateStrategy": "0xf4a0039F2d4a2EaD5216AbB6Ae4C4C3AA2dB9b82",
      "borrowingEnabled": true,
      "oracleDecimals": 8,
      "isBorrowableInIsolation": true,
      "decimals": 6,
      "symbol": "USDC",
      "isFrozen": false,
      "isActive": true,
      "aToken": "0x625E7708f30cA75bfd92586e17077590C60eb4cD",
      "reserveFactor": 1000,
      "variableDebtToken": "0xFCCf3cAbbe80101232d343252614b6A3eE81C989",
      "variableDebtTokenImpl": "0xa0d9C1E9E48Ca30c8d8C3B5D69FF5dc1f6DFfC24",
      "isSiloed": false,
      "isFlashloanable": false,
      "ltv": 8250,
      "liquidationThreshold": 8625,
      "oracle": "0xF096872672F44d6EBA71458D74fe67F9a77a23B9",
      "stableDebtToken": "0x307ffe186F84a3bc2613D1eA417A5737D69A7007",
      "oracleDescription": "USDC / USD",
      "liquidationBonus": 10400,
      "stableDebtTokenImpl": "0x893411580e590D62dDBca8a703d61Cc4A8c7b2b9"
    },
    "0x152b9d0FdC40C096757F570A51E494bd4b943E50": {
      "variableDebtTokenImpl": "0xa0d9C1E9E48Ca30c8d8C3B5D69FF5dc1f6DFfC24",
      "borrowCap": 900,
      "variableDebtToken": "0xA8669021776Bc142DfcA87c21b4A52595bCbB40a",
      "debtCeiling": 0,
      "borrowingEnabled": true,
      "oracleDescription": "BTC / USD",
      "oracleDecimals": 8,
      "isActive": true,
      "oracleLatestAnswer": 2683987600500,
      "underlying": "0x152b9d0FdC40C096757F570A51E494bd4b943E50",
      "supplyCap": 3000,
      "usageAsCollateralEnabled": true,
      "stableDebtTokenImpl": "0x893411580e590D62dDBca8a703d61Cc4A8c7b2b9",
      "liquidationBonus": 10650,
      "interestRateStrategy": "0x79a906e8c998d2fb5C5D66d23c4c5416Fe0168D6",
      "stableBorrowRateEnabled": false,
      "isFrozen": false,
      "aTokenImpl": "0x1E81af09001aD208BDa68FF022544dB2102A752d",
      "liquidationProtocolFee": 1000,
      "liquidationThreshold": 7500,
      "ltv": 7000,
      "oracle": "0x2779D32d5166BAaa2B2b658333bA7e6Ec0C65743",
      "eModeCategory": 0,
      "aToken": "0x8ffDf2DE812095b1D19CB146E4c004587C0A0692",
      "reserveFactor": 2000,
      "isFlashloanable": false,
      "isBorrowableInIsolation": false,
      "stableDebtToken": "0xa5e408678469d23efDB7694b1B0A85BB0669e8bd",
      "isSiloed": false,
      "symbol": "BTC.b",
      "decimals": 8
    },
    "0x5947BB275c521040051D82396192181b413227A3": {
      "isSiloed": false,
      "interestRateStrategy": "0x79a906e8c998d2fb5C5D66d23c4c5416Fe0168D6",
      "variableDebtTokenImpl": "0xa0d9C1E9E48Ca30c8d8C3B5D69FF5dc1f6DFfC24",
      "variableDebtToken": "0x953A573793604aF8d41F306FEb8274190dB4aE0e",
      "stableBorrowRateEnabled": false,
      "oracleLatestAnswer": 655828602,
      "reserveFactor": 2000,
      "stableDebtToken": "0x89D976629b7055ff1ca02b927BA3e020F22A44e4",
      "underlying": "0x5947BB275c521040051D82396192181b413227A3",
      "aTokenImpl": "0x1E81af09001aD208BDa68FF022544dB2102A752d",
      "oracleDecimals": 8,
      "liquidationProtocolFee": 1000,
      "debtCeiling": 0,
      "isActive": true,
      "isFrozen": false,
      "isFlashloanable": false,
      "stableDebtTokenImpl": "0x893411580e590D62dDBca8a703d61Cc4A8c7b2b9",
      "borrowingEnabled": true,
      "borrowCap": 220000,
      "decimals": 18,
      "eModeCategory": 0,
      "symbol": "LINK.e",
      "supplyCap": 440000,
      "aToken": "0x191c10Aa4AF7C30e871E70C95dB0E4eb77237530",
      "ltv": 5300,
      "oracleDescription": "LINK / USD",
      "usageAsCollateralEnabled": true,
      "oracle": "0x49ccd9ca821EfEab2b98c60dC60F518E765EDe9a",
      "liquidationThreshold": 6800,
      "isBorrowableInIsolation": false,
      "liquidationBonus": 10750
    },
    "0x50b7545627a5162F82A992c33b87aDc75187B218": {
      "ltv": 7000,
      "decimals": 8,
      "underlying": "0x50b7545627a5162F82A992c33b87aDc75187B218",
      "borrowingEnabled": true,
      "variableDebtTokenImpl": "0xa0d9C1E9E48Ca30c8d8C3B5D69FF5dc1f6DFfC24",
      "usageAsCollateralEnabled": true,
      "aTokenImpl": "0x1E81af09001aD208BDa68FF022544dB2102A752d",
      "isSiloed": false,
      "reserveFactor": 2000,
      "isFlashloanable": false,
      "supplyCap": 2000,
      "symbol": "WBTC.e",
      "isBorrowableInIsolation": false,
      "stableDebtToken": "0x633b207Dd676331c413D4C013a6294B0FE47cD0e",
      "oracle": "0x2779D32d5166BAaa2B2b658333bA7e6Ec0C65743",
      "isFrozen": false,
      "oracleDecimals": 8,
      "oracleLatestAnswer": 2683987600500,
      "debtCeiling": 0,
      "isActive": true,
      "liquidationBonus": 10625,
      "eModeCategory": 0,
      "stableBorrowRateEnabled": false,
      "stableDebtTokenImpl": "0x893411580e590D62dDBca8a703d61Cc4A8c7b2b9",
      "aToken": "0x078f358208685046a11C85e8ad32895DED33A249",
      "variableDebtToken": "0x92b42c66840C7AD907b4BF74879FF3eF7c529473",
      "liquidationProtocolFee": 1000,
      "oracleDescription": "BTC / USD",
      "borrowCap": 1100,
      "liquidationThreshold": 7500,
      "interestRateStrategy": "0x79a906e8c998d2fb5C5D66d23c4c5416Fe0168D6"
    },
    "0x5c49b268c9841AFF1Cc3B0a418ff5c3442eE3F3b": {
      "stableDebtTokenImpl": "0x893411580e590D62dDBca8a703d61Cc4A8c7b2b9",
      "stableBorrowRateEnabled": false,
      "oracleDescription": "MIMATIC / USD",
      "usageAsCollateralEnabled": true,
      "aToken": "0x8Eb270e296023E9D92081fdF967dDd7878724424",
      "stableDebtToken": "0x3EF10DFf4928279c004308EbADc4Db8B7620d6fc",
      "decimals": 18,
      "aTokenImpl": "0x1E81af09001aD208BDa68FF022544dB2102A752d",
      "eModeCategory": 1,
      "underlying": "0x5c49b268c9841AFF1Cc3B0a418ff5c3442eE3F3b",
      "liquidationProtocolFee": 1000,
      "oracle": "0x5D1F504211c17365CA66353442a74D4435A8b778",
      "isFlashloanable": false,
      "oracleLatestAnswer": 99452167,
      "variableDebtToken": "0xCE186F6Cccb0c955445bb9d10C59caE488Fea559",
      "liquidationThreshold": 8000,
      "isActive": true,
      "variableDebtTokenImpl": "0xa0d9C1E9E48Ca30c8d8C3B5D69FF5dc1f6DFfC24",
      "reserveFactor": 2000,
      "supplyCap": 700000,
      "debtCeiling": 200000000,
      "isFrozen": false,
      "borrowingEnabled": true,
      "oracleDecimals": 8,
      "borrowCap": 460000,
      "interestRateStrategy": "0xfab05a6aF585da2F96e21452F91E812452996BD3",
      "isSiloed": false,
      "ltv": 7500,
      "symbol": "MAI",
      "liquidationBonus": 10500,
      "isBorrowableInIsolation": false
    },
    "0x63a72806098Bd3D9520cC43356dD78afe5D386D9": {
      "stableBorrowRateEnabled": false,
      "oracleDescription": "AAVE / USD",
      "aToken": "0xf329e36C7bF6E5E86ce2150875a84Ce77f477375",
      "reserveFactor": 0,
      "eModeCategory": 0,
      "underlying": "0x63a72806098Bd3D9520cC43356dD78afe5D386D9",
      "oracleDecimals": 8,
      "isBorrowableInIsolation": false,
      "liquidationBonus": 11100,
      "liquidationProtocolFee": 1000,
      "usageAsCollateralEnabled": true,
      "variableDebtTokenImpl": "0xa0d9C1E9E48Ca30c8d8C3B5D69FF5dc1f6DFfC24",
      "isFrozen": false,
      "stableDebtToken": "0xfAeF6A702D15428E588d4C0614AEFb4348D83D48",
      "stableDebtTokenImpl": "0x893411580e590D62dDBca8a703d61Cc4A8c7b2b9",
      "supplyCap": 5800,
      "oracleLatestAnswer": 6413191200,
      "borrowCap": 0,
      "isActive": true,
      "ltv": 6200,
      "aTokenImpl": "0x1E81af09001aD208BDa68FF022544dB2102A752d",
      "isSiloed": false,
      "interestRateStrategy": "0x79a906e8c998d2fb5C5D66d23c4c5416Fe0168D6",
      "debtCeiling": 0,
      "variableDebtToken": "0xE80761Ea617F66F96274eA5e8c37f03960ecC679",
      "symbol": "AAVE.e",
      "liquidationThreshold": 9000,
      "borrowingEnabled": false,
      "isFlashloanable": false,
      "decimals": 18,
      "oracle": "0x3CA13391E9fb38a75330fb28f8cc2eB3D9ceceED"
    },
    "0x49D5c2BdFfac6CE2BFdB6640F4F80f226bc10bAB": {
      "ltv": 8000,
      "oracleDecimals": 8,
      "liquidationProtocolFee": 1000,
      "eModeCategory": 0,
      "symbol": "WETH.e",
      "stableDebtToken": "0xD8Ad37849950903571df17049516a5CD4cbE55F6",
      "variableDebtTokenImpl": "0xa0d9C1E9E48Ca30c8d8C3B5D69FF5dc1f6DFfC24",
      "debtCeiling": 0,
      "isActive": true,
      "isFrozen": false,
      "aTokenImpl": "0x1E81af09001aD208BDa68FF022544dB2102A752d",
      "isFlashloanable": false,
      "usageAsCollateralEnabled": true,
      "liquidationThreshold": 8250,
      "decimals": 18,
      "oracleLatestAnswer": 181755000000,
      "stableDebtTokenImpl": "0x893411580e590D62dDBca8a703d61Cc4A8c7b2b9",
      "underlying": "0x49D5c2BdFfac6CE2BFdB6640F4F80f226bc10bAB",
      "liquidationBonus": 10500,
      "supplyCap": 38000,
      "isSiloed": false,
      "oracleDescription": "ETH / USD",
      "interestRateStrategy": "0x271f5f8325051f22caDa18FfedD4a805584a232A",
      "isBorrowableInIsolation": false,
      "borrowingEnabled": true,
      "oracle": "0x976B3D034E162d8bD72D6b9C989d545b839003b0",
      "borrowCap": 20500,
      "variableDebtToken": "0x0c84331e39d6658Cd6e6b9ba04736cC4c4734351",
      "stableBorrowRateEnabled": false,
      "reserveFactor": 1500,
      "aToken": "0xe50fA9b3c56FfB159cB0FCA61F5c9D750e8128c8"
    },
    "0xD24C2Ad096400B6FBcd2ad8B24E7acBc21A1da64": {
      "liquidationBonus": 10500,
      "variableDebtTokenImpl": "0xa0d9C1E9E48Ca30c8d8C3B5D69FF5dc1f6DFfC24",
      "ltv": 7500,
      "isBorrowableInIsolation": false,
      "reserveFactor": 1000,
      "symbol": "FRAX",
      "isFlashloanable": false,
      "isActive": true,
      "interestRateStrategy": "0xfab05a6aF585da2F96e21452F91E812452996BD3",
      "decimals": 18,
      "variableDebtToken": "0x34e2eD44EF7466D5f9E0b782B5c08b57475e7907",
      "borrowCap": 1000000,
      "aTokenImpl": "0x1E81af09001aD208BDa68FF022544dB2102A752d",
      "oracle": "0xbBa56eF1565354217a3353a466edB82E8F25b08e",
      "oracleDescription": "FRAX / USD",
      "oracleLatestAnswer": 99836025,
      "debtCeiling": 100000000,
      "liquidationThreshold": 8000,
      "eModeCategory": 1,
      "borrowingEnabled": true,
      "stableBorrowRateEnabled": false,
      "usageAsCollateralEnabled": true,
      "oracleDecimals": 8,
      "isSiloed": false,
      "stableDebtTokenImpl": "0x893411580e590D62dDBca8a703d61Cc4A8c7b2b9",
      "supplyCap": 1500000,
      "isFrozen": false,
      "underlying": "0xD24C2Ad096400B6FBcd2ad8B24E7acBc21A1da64",
      "liquidationProtocolFee": 1000,
      "stableDebtToken": "0x78246294a4c6fBf614Ed73CcC9F8b875ca8eE841",
      "aToken": "0xc45A479877e1e9Dfe9FcD4056c699575a1045dAA"
    },
    "0xB31f66AA3C1e785363F0875A1B74E27b85FD66c7": {
      "usageAsCollateralEnabled": true,
      "underlying": "0xB31f66AA3C1e785363F0875A1B74E27b85FD66c7",
      "decimals": 18,
      "stableDebtToken": "0xF15F26710c827DDe8ACBA678682F3Ce24f2Fb56E",
      "liquidationProtocolFee": 1000,
      "isFlashloanable": false,
      "liquidationThreshold": 7300,
      "borrowCap": 2400000,
      "isFrozen": false,
      "variableDebtTokenImpl": "0xa0d9C1E9E48Ca30c8d8C3B5D69FF5dc1f6DFfC24",
      "oracle": "0x0A77230d17318075983913bC2145DB16C7366156",
      "reserveFactor": 2000,
      "ltv": 6800,
      "supplyCap": 3800000,
      "eModeCategory": 2,
      "aToken": "0x6d80113e533a2C0fe82EaBD35f1875DcEA89Ea97",
      "oracleDescription": "AVAX / USD",
      "oracleDecimals": 8,
      "interestRateStrategy": "0xc76EF342898f1AE7E6C4632627Df683FAD8563DD",
      "stableBorrowRateEnabled": false,
      "isBorrowableInIsolation": false,
      "variableDebtToken": "0x4a1c3aD6Ed28a636ee1751C69071f6be75DEb8B8",
      "liquidationBonus": 11000,
      "isSiloed": false,
      "isActive": true,
      "oracleLatestAnswer": 1460890000,
      "debtCeiling": 0,
      "borrowingEnabled": true,
      "symbol": "WAVAX",
      "aTokenImpl": "0x1E81af09001aD208BDa68FF022544dB2102A752d",
      "stableDebtTokenImpl": "0x893411580e590D62dDBca8a703d61Cc4A8c7b2b9"
    },
    "0xd586E7F844cEa2F87f50152665BCbc2C279D8d70": {
      "stableDebtToken": "0xd94112B5B62d53C9402e7A60289c6810dEF1dC9B",
      "liquidationThreshold": 8200,
      "supplyCap": 17000000,
      "oracleDecimals": 8,
      "isFrozen": false,
      "reserveFactor": 1000,
      "isBorrowableInIsolation": true,
      "isFlashloanable": false,
      "isActive": true,
      "isSiloed": false,
      "interestRateStrategy": "0xfab05a6aF585da2F96e21452F91E812452996BD3",
      "stableDebtTokenImpl": "0x893411580e590D62dDBca8a703d61Cc4A8c7b2b9",
      "oracleLatestAnswer": 99981137,
      "usageAsCollateralEnabled": true,
      "oracleDescription": "DAI / USD",
      "symbol": "DAI.e",
      "debtCeiling": 0,
      "ltv": 7500,
      "borrowingEnabled": true,
      "borrowCap": 17000000,
      "liquidationProtocolFee": 1000,
      "variableDebtToken": "0x8619d80FB0141ba7F184CbF22fd724116D9f7ffC",
      "decimals": 18,
      "eModeCategory": 1,
      "oracle": "0x51D7180edA2260cc4F6e4EebB82FEF5c3c2B8300",
      "stableBorrowRateEnabled": true,
      "underlying": "0xd586E7F844cEa2F87f50152665BCbc2C279D8d70",
      "liquidationBonus": 10500,
      "aToken": "0x82E64f49Ed5EC1bC6e43DAD4FC8Af9bb3A2312EE",
      "variableDebtTokenImpl": "0xa0d9C1E9E48Ca30c8d8C3B5D69FF5dc1f6DFfC24",
      "aTokenImpl": "0x1E81af09001aD208BDa68FF022544dB2102A752d"
    },
    "0x9702230A8Ea53601f5cD2dc00fDBc13d4dF4A8c7": {
      "decimals": 6,
      "liquidationBonus": 10500,
      "isFlashloanable": false,
      "symbol": "USDt",
      "underlying": "0x9702230A8Ea53601f5cD2dc00fDBc13d4dF4A8c7",
      "isActive": true,
      "debtCeiling": 500000000,
      "liquidationProtocolFee": 1000,
      "oracleDescription": "USDT / USD",
      "stableBorrowRateEnabled": true,
      "stableDebtTokenImpl": "0x893411580e590D62dDBca8a703d61Cc4A8c7b2b9",
      "variableDebtToken": "0xfb00AC187a8Eb5AFAE4eACE434F493Eb62672df7",
      "aToken": "0x6ab707Aca953eDAeFBc4fD23bA73294241490620",
      "oracleDecimals": 8,
      "isSiloed": false,
      "isFrozen": false,
      "oracle": "0xEBE676ee90Fe1112671f19b6B7459bC678B67e8a",
      "borrowCap": 140000000,
      "oracleLatestAnswer": 100058000,
      "variableDebtTokenImpl": "0xa0d9C1E9E48Ca30c8d8C3B5D69FF5dc1f6DFfC24",
      "usageAsCollateralEnabled": true,
      "eModeCategory": 1,
      "reserveFactor": 1000,
      "liquidationThreshold": 8100,
      "isBorrowableInIsolation": true,
      "aTokenImpl": "0x1E81af09001aD208BDa68FF022544dB2102A752d",
      "borrowingEnabled": true,
      "ltv": 7500,
      "supplyCap": 200000000,
      "stableDebtToken": "0x70eFfc565DB6EEf7B927610155602d31b670e802",
      "interestRateStrategy": "0xfab05a6aF585da2F96e21452F91E812452996BD3"
    },
    "0x2b2C81e08f1Af8835a78Bb2A90AE924ACE0eA4bE": {
      "debtCeiling": 0,
      "ltv": 2000,
      "liquidationBonus": 11000,
      "reserveFactor": 1000,
      "oracleLatestAnswer": 1583511307,
      "borrowingEnabled": false,
      "underlying": "0x2b2C81e08f1Af8835a78Bb2A90AE924ACE0eA4bE",
      "liquidationThreshold": 3000,
      "isFrozen": false,
      "stableBorrowRateEnabled": false,
      "aTokenImpl": "0x1E81af09001aD208BDa68FF022544dB2102A752d",
      "isBorrowableInIsolation": false,
      "supplyCap": 2000000,
      "aToken": "0x513c7E3a9c69cA3e22550eF58AC1C0088e918FFf",
      "symbol": "sAVAX",
      "interestRateStrategy": "0x79a906e8c998d2fb5C5D66d23c4c5416Fe0168D6",
      "eModeCategory": 2,
      "isSiloed": false,
      "isFlashloanable": false,
      "liquidationProtocolFee": 1000,
      "usageAsCollateralEnabled": true,
      "stableDebtToken": "0x08Cb71192985E936C7Cd166A8b268035e400c3c3",
      "borrowCap": 0,
      "variableDebtToken": "0x77CA01483f379E58174739308945f044e1a764dc",
      "decimals": 18,
      "isActive": true,
      "oracle": "0xc9245871D69BF4c36c6F2D15E0D68Ffa883FE1A7",
      "variableDebtTokenImpl": "0xa0d9C1E9E48Ca30c8d8C3B5D69FF5dc1f6DFfC24",
      "stableDebtTokenImpl": "0x893411580e590D62dDBca8a703d61Cc4A8c7b2b9"
    }
  }
}